measurepy/__init__.py
measurepy/multimeasure.py
measurepy/regression.py
measurepy-0.1.dist-info/DESCRIPTION.rst
measurepy-0.1.dist-info/METADATA
measurepy-0.1.dist-info/RECORD
measurepy-0.1.dist-info/WHEEL
measurepy-0.1.dist-info/metadata.json
measurepy-0.1.dist-info/top_level.txt
