Metadata-Version: 2.0
Name: measurepy
Version: 0.1
Summary: A python module to boost first-step data analysis after measurements.
Home-page: http://github.com/JasonQSY/measurepy
Author: JasonQSY
Author-email: jasonsyqian@gmail.com
License: MIT
Platform: UNKNOWN
Requires-Dist: matplotlib
Requires-Dist: numpy
Requires-Dist: scipy
